word2num/__init__.py
word2num/word2num.py
word2num/languages/__init__.py
word2num/languages/en/__init__.py
word2num/languages/en/parser.py
word2num/languages/en/vocabulary.py
word2num/languages/en/word_matcher.py
word2num/languages/es/__init__.py
word2num/languages/es/parser.py
word2num/languages/es/vocabulary.py
word2num/languages/es/word_matcher.py
word2num/parsing/__init__.py
word2num/parsing/parser.py
word2num/parsing/standard_parser.py
word2num/tokenization/__init__.py
word2num/tokenization/base_tokenizer.py
word2num/tokenization/simple_tokenizer.py
word2num/word_matching/__init__.py
word2num/word_matching/vocabulary.py
word2num/word_matching/word_matcher.py
word2num-0.1.2.dist-info/LICENSE.txt
word2num-0.1.2.dist-info/METADATA
word2num-0.1.2.dist-info/WHEEL
word2num-0.1.2.dist-info/top_level.txt
word2num-0.1.2.dist-info/RECORD
